{
  "date": "2024-12-10",
  "status": "complete",
  "dynamic_strikes": {
    "status": "complete",
    "contracts": 22,
    "strikes": [
      600,
      601,
      602,
      603,
      604,
      605,
      606,
      607,
      608,
      609,
      610
    ],
    "last_strike": 609,
    "volume_filtered": 0
  },
  "stats": {
    "total_contracts": 22,
    "total_ohlc_bars": 1606,
    "total_greeks_bars": 1738,
    "total_iv_bars": 1738,
    "total_iv_nulls": 364,
    "spy_open": 605.3699951171875,
    "atm_strike": 605,
    "atm_iv": 0.09218518518518518,
    "strike_selection_method": "dynamic",
    "strikes_per_side": 5,
    "volume_filtered_count": 0,
    "coverage": 93.58974358974359
  },
  "iv_stats": {
    "total_points": 1738,
    "valid_ivs": 1374,
    "zero_ivs": 364,
    "null_stored": 364
  },
  "errors": []
}