{
  "date": "2024-08-12",
  "status": "complete",
  "dynamic_strikes": {
    "status": "complete",
    "contracts": 34,
    "strikes": [
      526,
      527,
      528,
      529,
      530,
      531,
      532,
      533,
      534,
      535,
      536,
      537,
      538,
      539,
      540,
      541,
      542
    ],
    "last_strike": 540,
    "volume_filtered": 0
  },
  "stats": {
    "total_contracts": 34,
    "total_ohlc_bars": 2411,
    "total_greeks_bars": 2686,
    "total_iv_bars": 2686,
    "total_iv_nulls": 399,
    "spy_open": 534.2100219726562,
    "atm_strike": 534,
    "atm_iv": 0.24716206896551723,
    "strike_selection_method": "dynamic",
    "strikes_per_side": 8,
    "volume_filtered_count": 0,
    "coverage": 90.91251885369532
  },
  "iv_stats": {
    "total_points": 2686,
    "valid_ivs": 2287,
    "zero_ivs": 399,
    "null_stored": 399
  },
  "errors": []
}