{
  "date": "2023-06-20",
  "status": "complete",
  "dynamic_strikes": {
    "status": "complete",
    "contracts": 22,
    "strikes": [
      432,
      433,
      434,
      435,
      436,
      437,
      438,
      439,
      440,
      441,
      442
    ],
    "last_strike": 441,
    "volume_filtered": 0
  },
  "stats": {
    "total_contracts": 22,
    "total_ohlc_bars": 1644,
    "total_greeks_bars": 1738,
    "total_iv_bars": 1738,
    "total_iv_nulls": 301,
    "spy_open": 437.45001220703125,
    "atm_strike": 437,
    "atm_iv": 0.14829,
    "strike_selection_method": "dynamic",
    "strikes_per_side": 5,
    "volume_filtered_count": 0,
    "coverage": 95.8041958041958
  },
  "iv_stats": {
    "total_points": 1738,
    "valid_ivs": 1437,
    "zero_ivs": 301,
    "null_stored": 301
  },
  "errors": []
}